pyqt5_fugueicons/__init__.py
pyqt5_fugueicons/icon.py
pyqt5_fugueicons/movie.py
pyqt5_fugueicons/resources.py
pyqt5_fugueicons-3.5.6.2.dist-info/LICENSE
pyqt5_fugueicons-3.5.6.2.dist-info/METADATA
pyqt5_fugueicons-3.5.6.2.dist-info/WHEEL
pyqt5_fugueicons-3.5.6.2.dist-info/top_level.txt
pyqt5_fugueicons-3.5.6.2.dist-info/RECORD
