Metadata-Version: 2.1
Name: pyqt5-fugueicons
Version: 3.5.6.2
Summary: Fugue Icons for PyQt5
Home-page: https://github.com/glourencoffee/pyqt5_fugueicons
Author: Giovanni Lourenço
Author-email: gvnl.developer@outlook.com
License: MIT
Keywords: pyqt5,icons
Requires-Python: >=3.6
License-File: LICENSE
Requires-Dist: PyQt5
